greenbone/scap/api/__init__.py
greenbone/scap/api/__version__.py
greenbone/scap/api/app.py
greenbone/scap/api/cve/__init__.py
greenbone/scap/api/cve/api.py
greenbone/scap/api/cve/data.py
greenbone/scap/api/cve/dependencies.py
greenbone/scap/api/cve/schema.py
greenbone/scap/api/errors.py
greenbone/scap/api/main.py
greenbone_scap_api-25.3.1.dist-info/LICENSE
greenbone_scap_api-25.3.1.dist-info/METADATA
greenbone_scap_api-25.3.1.dist-info/WHEEL
greenbone_scap_api-25.3.1.dist-info/entry_points.txt
greenbone_scap_api-25.3.1.dist-info/RECORD
