Metadata-Version: 2.3
Name: greenbone-scap-api
Version: 25.3.1
Summary: REST API on top of greenbone-scap
License: AGPL-3.0-or-later
Author: Greenbone
Author-email: info@greenbone.net
Requires-Python: >=3.11,<4.0
Classifier: Development Status :: 4 - Beta
Classifier: Environment :: Console
Classifier: Intended Audience :: Developers
Classifier: License :: OSI Approved :: GNU Affero General Public License v3 or later (AGPLv3+)
Classifier: Operating System :: OS Independent
Classifier: Programming Language :: Python :: 3
Classifier: Programming Language :: Python :: 3.11
Classifier: Programming Language :: Python :: 3.12
Classifier: Programming Language :: Python :: 3.13
Classifier: Topic :: Software Development :: Libraries :: Python Modules
Requires-Dist: fastapi (>=0.110,<0.116)
Requires-Dist: greenbone-scap (>=0.1,<0.4)
Requires-Dist: shtab (>=1.6.5)
Requires-Dist: uvicorn[standard] (>=0.29,<0.35)
